{
  "updated": "Jul 20 2026",
  "currency": "C$",
  "history": [
    {
      "d": "Jun 04 2026",
      "v": 1665
    },
    {
      "d": "Jun 05 2026",
      "v": 1644
    },
    {
      "d": "Jun 06 2026",
      "v": 1712
    },
    {
      "d": "Jun 07 2026",
      "v": 1859,
      "cards": {
        "Luffy OP13-118 SP": 730,
        "Mega Gardevoir ex MEP 032": 354,
        "Mega Hawlucha ex 268/217": 240,
        "Eevee 074/131": 188,
        "Deoxys VSTAR GG46": 200,
        "Espeon": 41,
        "Monkey D. Luffy ST26-005": 7,
        "Flareon": 95,
        "Nico Robin ST26-003": 4
      }
    },
    {
      "d": "Jun 08 2026",
      "v": 1903,
      "cards": {
        "Luffy OP13-118 SP": 730,
        "Mega Gardevoir ex MEP 032": 354,
        "Mega Hawlucha ex 268/217": 231,
        "Eevee 074/131": 238,
        "Deoxys VSTAR GG46": 230,
        "Flareon": 116,
        "Nico Robin ST26-003": 4
      }
    },
    {
      "d": "Jun 09 2026",
      "v": 1929,
      "cards": {
        "Luffy OP13-118 SP": 730,
        "Mega Gardevoir ex MEP 032": 354,
        "Mega Hawlucha ex 268/217": 231,
        "Eevee 074/131": 238,
        "Deoxys VSTAR GG46": 263,
        "Flareon": 109,
        "Nico Robin ST26-003": 4
      }
    },
    {
      "d": "Jun 10 2026",
      "v": 1929,
      "cards": {
        "Luffy OP13-118 SP": 730,
        "Mega Gardevoir ex MEP 032": 354,
        "Mega Hawlucha ex 268/217": 231,
        "Eevee 074/131": 238,
        "Deoxys VSTAR GG46": 263,
        "Flareon": 109,
        "Nico Robin ST26-003": 4
      }
    },
    {
      "d": "Jun 11 2026",
      "v": 1929,
      "cards": {
        "Luffy OP13-118 SP": 730,
        "Mega Gardevoir ex MEP 032": 354,
        "Mega Hawlucha ex 268/217": 231,
        "Eevee 074/131": 238,
        "Deoxys VSTAR GG46": 263,
        "Flareon": 109,
        "Nico Robin ST26-003": 4
      }
    },
    {
      "d": "Jun 12 2026",
      "v": 1929,
      "cards": {
        "Luffy OP13-118 SP": 730,
        "Mega Gardevoir ex MEP 032": 354,
        "Mega Hawlucha ex 268/217": 231,
        "Eevee 074/131": 238,
        "Deoxys VSTAR GG46": 263,
        "Flareon": 109,
        "Nico Robin ST26-003": 4
      }
    },
    {
      "d": "Jun 13 2026",
      "v": 1929,
      "cards": {
        "Luffy OP13-118 SP": 730,
        "Mega Gardevoir ex MEP 032": 354,
        "Mega Hawlucha ex 268/217": 231,
        "Eevee 074/131": 238,
        "Deoxys VSTAR GG46": 263,
        "Flareon": 109,
        "Nico Robin ST26-003": 4
      }
    },
    {
      "d": "Jun 14 2026",
      "v": 2727,
      "cards": {
        "Luffy OP13-118 SP": 730,
        "Marshadow & Machamp GX 199": 391,
        "Mega Gardevoir ex MEP 032": 368,
        "Mega Hawlucha ex 268/217": 223,
        "Eevee 074/131": 237,
        "Flareon": 109,
        "Mega Lucario ex MEP 033": 510,
        "Luffy OP16-034": 58,
        "Dark Magneton 11/82": 102
      }
    },
    {
      "d": "Jun 15 2026",
      "v": 2756,
      "cards": {
        "Luffy OP13-118 SP": 730,
        "Marshadow & Machamp GX 199": 401,
        "Mega Gardevoir ex MEP 032": 367,
        "Mega Hawlucha ex 268/217": 231,
        "Eevee 074/131": 237,
        "Flareon": 109,
        "Mega Lucario ex MEP 033": 510,
        "Luffy OP16-034": 69,
        "Dark Magneton 11/82": 102
      }
    },
    {
      "d": "Jun 16 2026",
      "v": 2770,
      "cards": {
        "Luffy OP13-118 SP": 730,
        "Marshadow & Machamp GX 199": 408,
        "Mega Gardevoir ex MEP 032": 368,
        "Mega Hawlucha ex 268/217": 231,
        "Eevee 074/131": 237,
        "Flareon": 109,
        "Mega Lucario ex MEP 033": 510,
        "Luffy OP16-034": 69,
        "Dark Magneton 11/82": 109
      }
    },
    {
      "d": "Jun 17 2026",
      "v": 2773,
      "cards": {
        "Luffy OP13-118 SP": 730,
        "Marshadow & Machamp GX 199": 405,
        "Mega Gardevoir ex MEP 032": 368,
        "Mega Hawlucha ex 268/217": 231,
        "Eevee 074/131": 237,
        "Flareon": 118,
        "Mega Lucario ex MEP 033": 511,
        "Luffy OP16-034": 65,
        "Dark Magneton 11/82": 109
      }
    },
    {
      "d": "Jun 18 2026",
      "v": 2760,
      "cards": {
        "Luffy OP13-118 SP": 730,
        "Marshadow & Machamp GX 199": 408,
        "Mega Gardevoir ex MEP 032": 368,
        "Mega Hawlucha ex 268/217": 231,
        "Eevee 074/131": 231,
        "Flareon": 109,
        "Mega Lucario ex MEP 033": 510,
        "Luffy OP16-034": 65,
        "Dark Magneton 11/82": 109
      }
    },
    {
      "d": "Jun 19 2026",
      "v": 2768,
      "cards": {
        "Luffy OP13-118 SP": 730,
        "Marshadow & Machamp GX 199": 408,
        "Mega Gardevoir ex MEP 032": 369,
        "Mega Hawlucha ex 268/217": 231,
        "Eevee 074/131": 231,
        "Flareon": 116,
        "Mega Lucario ex MEP 033": 510,
        "Luffy OP16-034": 65,
        "Dark Magneton 11/82": 109
      }
    },
    {
      "d": "Jun 20 2026",
      "v": 2758,
      "cards": {
        "Luffy OP13-118 SP": 730,
        "Marshadow & Machamp GX 199": 408,
        "Mega Gardevoir ex MEP 032": 368,
        "Mega Hawlucha ex 268/217": 231,
        "Eevee 074/131": 231,
        "Flareon": 109,
        "Mega Lucario ex MEP 033": 510,
        "Luffy OP16-034": 63,
        "Dark Magneton 11/82": 109
      }
    },
    {
      "d": "Jun 21 2026",
      "v": 2748,
      "cards": {
        "Luffy OP13-118 SP": 730,
        "Marshadow & Machamp GX 199": 408,
        "Mega Gardevoir ex MEP 032": 369,
        "Mega Hawlucha ex 268/217": 231,
        "Eevee 074/131": 224,
        "Flareon": 109,
        "Mega Lucario ex MEP 033": 511,
        "Luffy OP16-034": 58,
        "Dark Magneton 11/82": 109
      }
    },
    {
      "d": "Jun 22 2026",
      "v": 2756,
      "cards": {
        "Luffy OP13-118 SP": 730,
        "Marshadow & Machamp GX 199": 408,
        "Mega Gardevoir ex MEP 032": 368,
        "Mega Hawlucha ex 268/217": 231,
        "Eevee 074/131": 231,
        "Flareon": 112,
        "Mega Lucario ex MEP 033": 510,
        "Luffy OP16-034": 58,
        "Dark Magneton 11/82": 109
      }
    },
    {
      "d": "Jun 23 2026",
      "v": 2741,
      "cards": {
        "Luffy OP13-118 SP": 730,
        "Marshadow & Machamp GX 199": 408,
        "Mega Gardevoir ex MEP 032": 369,
        "Mega Hawlucha ex 268/217": 231,
        "Eevee 074/131": 231,
        "Flareon": 109,
        "Mega Lucario ex MEP 033": 506,
        "Luffy OP16-034": 58,
        "Dark Magneton 11/82": 100
      }
    },
    {
      "d": "Jun 24 2026",
      "v": 2749,
      "cards": {
        "Luffy OP13-118 SP": 730,
        "Marshadow & Machamp GX 199": 408,
        "Mega Gardevoir ex MEP 032": 368,
        "Mega Hawlucha ex 268/217": 231,
        "Eevee 074/131": 230,
        "Flareon": 109,
        "Mega Lucario ex MEP 033": 506,
        "Luffy OP16-034": 58,
        "Dark Magneton 11/82": 109
      }
    },
    {
      "d": "Jun 25 2026",
      "v": 2732,
      "cards": {
        "Luffy OP13-118 SP": 730,
        "Marshadow & Machamp GX 199": 408,
        "Mega Gardevoir ex MEP 032": 357,
        "Mega Hawlucha ex 268/217": 231,
        "Eevee 074/131": 224,
        "Flareon": 109,
        "Mega Lucario ex MEP 033": 506,
        "Luffy OP16-034": 58,
        "Dark Magneton 11/82": 109
      }
    },
    {
      "d": "Jun 26 2026",
      "v": 2743,
      "cards": {
        "Luffy OP13-118 SP": 730,
        "Marshadow & Machamp GX 199": 408,
        "Mega Gardevoir ex MEP 032": 368,
        "Mega Hawlucha ex 268/217": 231,
        "Eevee 074/131": 224,
        "Flareon": 109,
        "Mega Lucario ex MEP 033": 506,
        "Luffy OP16-034": 58,
        "Dark Magneton 11/82": 109
      }
    },
    {
      "d": "Jun 27 2026",
      "v": 2753,
      "cards": {
        "Luffy OP13-118 SP": 730,
        "Marshadow & Machamp GX 199": 408,
        "Mega Gardevoir ex MEP 032": 368,
        "Mega Hawlucha ex 268/217": 231,
        "Eevee 074/131": 224,
        "Flareon": 109,
        "Mega Lucario ex MEP 033": 510,
        "Luffy OP16-034": 58,
        "Dark Magneton 11/82": 116
      }
    },
    {
      "d": "Jun 28 2026",
      "v": 2758,
      "cards": {
        "Luffy OP13-118 SP": 730,
        "Marshadow & Machamp GX 199": 408,
        "Mega Gardevoir ex MEP 032": 368,
        "Mega Hawlucha ex 268/217": 231,
        "Eevee 074/131": 229,
        "Flareon": 109,
        "Mega Lucario ex MEP 033": 517,
        "Luffy OP16-034": 58,
        "Dark Magneton 11/82": 109
      }
    },
    {
      "d": "Jun 29 2026",
      "v": 2735,
      "cards": {
        "Luffy OP13-118 SP": 730,
        "Marshadow & Machamp GX 199": 381,
        "Mega Gardevoir ex MEP 032": 368,
        "Mega Hawlucha ex 268/217": 231,
        "Eevee 074/131": 229,
        "Flareon": 109,
        "Mega Lucario ex MEP 033": 506,
        "Luffy OP16-034": 58,
        "Dark Magneton 11/82": 122
      }
    },
    {
      "d": "Jun 30 2026",
      "v": 2765,
      "cards": {
        "Luffy OP13-118 SP": 730,
        "Marshadow & Machamp GX 199": 408,
        "Mega Gardevoir ex MEP 032": 368,
        "Mega Hawlucha ex 268/217": 231,
        "Eevee 074/131": 229,
        "Flareon": 109,
        "Mega Lucario ex MEP 033": 510,
        "Luffy OP16-034": 58,
        "Dark Magneton 11/82": 122
      }
    },
    {
      "d": "Jul 01 2026",
      "v": 2756,
      "cards": {
        "Luffy OP13-118 SP": 730,
        "Marshadow & Machamp GX 199": 408,
        "Mega Gardevoir ex MEP 032": 368,
        "Mega Hawlucha ex 268/217": 231,
        "Eevee 074/131": 224,
        "Flareon": 108,
        "Mega Lucario ex MEP 033": 506,
        "Luffy OP16-034": 58,
        "Dark Magneton 11/82": 122
      }
    },
    {
      "d": "Jul 02 2026",
      "v": 2760,
      "cards": {
        "Luffy OP13-118 SP": 730,
        "Marshadow & Machamp GX 199": 408,
        "Mega Gardevoir ex MEP 032": 368,
        "Mega Hawlucha ex 268/217": 231,
        "Eevee 074/131": 224,
        "Flareon": 109,
        "Mega Lucario ex MEP 033": 510,
        "Luffy OP16-034": 58,
        "Dark Magneton 11/82": 122
      }
    },
    {
      "d": "Jul 03 2026",
      "v": 2750,
      "cards": {
        "Luffy OP13-118 SP": 730,
        "Marshadow & Machamp GX 199": 408,
        "Mega Gardevoir ex MEP 032": 368,
        "Mega Hawlucha ex 268/217": 231,
        "Eevee 074/131": 230,
        "Flareon": 109,
        "Mega Lucario ex MEP 033": 510,
        "Luffy OP16-034": 58,
        "Dark Magneton 11/82": 107
      }
    },
    {
      "d": "Jul 04 2026",
      "v": 2750,
      "cards": {
        "Luffy OP13-118 SP": 730,
        "Marshadow & Machamp GX 199": 408,
        "Mega Gardevoir ex MEP 032": 368,
        "Mega Hawlucha ex 268/217": 231,
        "Eevee 074/131": 230,
        "Flareon": 109,
        "Mega Lucario ex MEP 033": 510,
        "Luffy OP16-034": 58,
        "Dark Magneton 11/82": 107
      }
    },
    {
      "d": "Jul 05 2026",
      "v": 2755,
      "cards": {
        "Luffy OP13-118 SP": 730,
        "Marshadow & Machamp GX 199": 408,
        "Mega Gardevoir ex MEP 032": 367,
        "Mega Hawlucha ex 268/217": 231,
        "Eevee 074/131": 235,
        "Flareon": 109,
        "Mega Lucario ex MEP 033": 510,
        "Luffy OP16-034": 58,
        "Dark Magneton 11/82": 107
      }
    },
    {
      "d": "Jul 06 2026",
      "v": 2755,
      "cards": {
        "Luffy OP13-118 SP": 730,
        "Marshadow & Machamp GX 199": 408,
        "Mega Gardevoir ex MEP 032": 367,
        "Mega Hawlucha ex 268/217": 231,
        "Eevee 074/131": 235,
        "Flareon": 109,
        "Mega Lucario ex MEP 033": 510,
        "Luffy OP16-034": 58,
        "Dark Magneton 11/82": 107
      }
    },
    {
      "d": "Jul 07 2026",
      "v": 2755,
      "cards": {
        "Luffy OP13-118 SP": 730,
        "Marshadow & Machamp GX 199": 408,
        "Mega Gardevoir ex MEP 032": 367,
        "Mega Hawlucha ex 268/217": 231,
        "Eevee 074/131": 235,
        "Flareon": 109,
        "Mega Lucario ex MEP 033": 510,
        "Luffy OP16-034": 58,
        "Dark Magneton 11/82": 107
      }
    },
    {
      "d": "Jul 08 2026",
      "v": 2764,
      "cards": {
        "Luffy OP13-118 SP": 730,
        "Marshadow & Machamp GX 199": 408,
        "Mega Gardevoir ex MEP 032": 368,
        "Mega Hawlucha ex 268/217": 231,
        "Eevee 074/131": 235,
        "Flareon": 109,
        "Mega Lucario ex MEP 033": 510,
        "Luffy OP16-034": 58,
        "Dark Magneton 11/82": 116
      }
    },
    {
      "d": "Jul 09 2026",
      "v": 2764,
      "cards": {
        "Luffy OP13-118 SP": 730,
        "Marshadow & Machamp GX 199": 408,
        "Mega Gardevoir ex MEP 032": 368,
        "Mega Hawlucha ex 268/217": 231,
        "Eevee 074/131": 235,
        "Flareon": 109,
        "Mega Lucario ex MEP 033": 510,
        "Luffy OP16-034": 58,
        "Dark Magneton 11/82": 116
      }
    },
    {
      "d": "Jul 10 2026",
      "v": 2764,
      "cards": {
        "Luffy OP13-118 SP": 730,
        "Marshadow & Machamp GX 199": 408,
        "Mega Gardevoir ex MEP 032": 368,
        "Mega Hawlucha ex 268/217": 231,
        "Eevee 074/131": 235,
        "Flareon": 109,
        "Mega Lucario ex MEP 033": 510,
        "Luffy OP16-034": 58,
        "Dark Magneton 11/82": 116
      }
    },
    {
      "d": "Jul 11 2026",
      "v": 2756,
      "cards": {
        "Luffy OP13-118 SP": 730,
        "Marshadow & Machamp GX 199": 408,
        "Mega Gardevoir ex MEP 032": 360,
        "Mega Hawlucha ex 268/217": 231,
        "Eevee 074/131": 235,
        "Flareon": 109,
        "Mega Lucario ex MEP 033": 510,
        "Luffy OP16-034": 58,
        "Dark Magneton 11/82": 116
      }
    },
    {
      "d": "Jul 12 2026",
      "v": 2749,
      "cards": {
        "Luffy OP13-118 SP": 730,
        "Marshadow & Machamp GX 199": 408,
        "Mega Gardevoir ex MEP 032": 360,
        "Mega Hawlucha ex 268/217": 231,
        "Eevee 074/131": 235,
        "Flareon": 109,
        "Mega Lucario ex MEP 033": 510,
        "Luffy OP16-034": 58,
        "Dark Magneton 11/82": 109
      }
    },
    {
      "d": "Jul 13 2026",
      "v": 2756,
      "cards": {
        "Luffy OP13-118 SP": 730,
        "Marshadow & Machamp GX 199": 408,
        "Mega Gardevoir ex MEP 032": 360,
        "Mega Hawlucha ex 268/217": 231,
        "Eevee 074/131": 235,
        "Flareon": 109,
        "Mega Lucario ex MEP 033": 510,
        "Luffy OP16-034": 58,
        "Dark Magneton 11/82": 116
      }
    },
    {
      "d": "Jul 14 2026",
      "v": 2749,
      "cards": {
        "Luffy OP13-118 SP": 730,
        "Marshadow & Machamp GX 199": 408,
        "Mega Gardevoir ex MEP 032": 352,
        "Mega Hawlucha ex 268/217": 231,
        "Eevee 074/131": 235,
        "Flareon": 109,
        "Mega Lucario ex MEP 033": 510,
        "Luffy OP16-034": 58,
        "Dark Magneton 11/82": 116
      }
    },
    {
      "d": "Jul 15 2026",
      "v": 2750,
      "cards": {
        "Luffy OP13-118 SP": 730,
        "Marshadow & Machamp GX 199": 408,
        "Mega Gardevoir ex MEP 032": 352,
        "Mega Hawlucha ex 268/217": 231,
        "Eevee 074/131": 235,
        "Flareon": 109,
        "Mega Lucario ex MEP 033": 510,
        "Luffy OP16-034": 58,
        "Dark Magneton 11/82": 117
      }
    },
    {
      "d": "Jul 16 2026",
      "v": 2748,
      "cards": {
        "Luffy OP13-118 SP": 730,
        "Marshadow & Machamp GX 199": 408,
        "Mega Gardevoir ex MEP 032": 352,
        "Mega Hawlucha ex 268/217": 231,
        "Eevee 074/131": 235,
        "Flareon": 107,
        "Mega Lucario ex MEP 033": 510,
        "Luffy OP16-034": 58,
        "Dark Magneton 11/82": 117
      }
    },
    {
      "d": "Jul 17 2026",
      "v": 2750,
      "cards": {
        "Luffy OP13-118 SP": 730,
        "Marshadow & Machamp GX 199": 408,
        "Mega Gardevoir ex MEP 032": 352,
        "Mega Hawlucha ex 268/217": 231,
        "Eevee 074/131": 235,
        "Flareon": 109,
        "Mega Lucario ex MEP 033": 510,
        "Luffy OP16-034": 58,
        "Dark Magneton 11/82": 117
      }
    },
    {
      "d": "Jul 18 2026",
      "v": 2745,
      "cards": {
        "Luffy OP13-118 SP": 730,
        "Marshadow & Machamp GX 199": 408,
        "Mega Gardevoir ex MEP 032": 352,
        "Mega Hawlucha ex 268/217": 231,
        "Eevee 074/131": 230,
        "Flareon": 109,
        "Mega Lucario ex MEP 033": 510,
        "Luffy OP16-034": 58,
        "Dark Magneton 11/82": 117
      }
    },
    {
      "d": "Jul 19 2026",
      "v": 2755,
      "cards": {
        "Luffy OP13-118 SP": 730,
        "Marshadow & Machamp GX 199": 408,
        "Mega Gardevoir ex MEP 032": 352,
        "Mega Hawlucha ex 268/217": 231,
        "Eevee 074/131": 235,
        "Flareon": 109,
        "Mega Lucario ex MEP 033": 510,
        "Luffy OP16-034": 58,
        "Dark Magneton 11/82": 122
      }
    },
    {
      "d": "Jul 20 2026",
      "v": 2755,
      "cards": {
        "Luffy OP13-118 SP": 730,
        "Marshadow & Machamp GX 199": 408,
        "Mega Gardevoir ex MEP 032": 352,
        "Mega Hawlucha ex 268/217": 231,
        "Eevee 074/131": 235,
        "Flareon": 109,
        "Mega Lucario ex MEP 033": 510,
        "Luffy OP16-034": 58,
        "Dark Magneton 11/82": 122
      }
    }
  ],
  "holdings": [
    {
      "ticker": "$LUFFY",
      "name": "Luffy OP13-118 SP · JP Wanted · CGC Pristine 10",
      "cost": 261,
      "prev": 730,
      "now": 730,
      "color": "#28f5a8",
      "floor": 600,
      "queries": [
        "luffy OP13-118 SP wanted CGC -manga -alt -english -lot",
        "monkey d luffy OP13-118 japanese CGC pristine -manga -alt -lot"
      ]
    },
    {
      "ticker": "$MCHAMP",
      "name": "Marshadow & Machamp GX 199 · Unbroken Bonds FA · PSA 9",
      "cost": 350,
      "prev": 408.0,
      "now": 408.0,
      "color": "#c0392b",
      "floor": 100,
      "ceil": 600,
      "queries": [
        "marshadow machamp GX 199 full art PSA 9 -lot -secret -rainbow",
        "marshadow machamp GX unbroken bonds 199 PSA 9 -lot"
      ],
      "listings": [
        {
          "t": "Pokémon Marshadow & Machamp GX 199/214 Unbroken Bonds Full Art Holo PSA 9",
          "p": 408,
          "u": "https://www.ebay.com/itm/277810238019?_skw=marshadow+machamp+GX+199+full+art+PSA+9+-lot+-secret+-rainbow&epid=9065727749&itmmeta=01KXZPD5577YV9WW8KA1EW7MRJ&hash=item40aec7d243:g:FMQAAeSwpZxpuNDO&itmprp=enc%3AAQALAAABIGfYFPkwiKCW4ZNSs2u11xCiUv3MZpIgyCTohr2H3X8ExnQpIlaZkbhtUuV66ltqb7Hb2llmzYY%2FydL7dQLBfgcGHV0PHPb5Thpyq0Wd1HsCZN7XA2VqN1%2F4g%2FB0G%2BWbCt3htoZzsJnptnkRJI00VLKJSRQPeN3RU4uoLg%2FYwqlpCS%2BRvwWwjP5jrVjjBPofN%2FUM3XlHdexL9qgqRoel1cFZT72v4Do6Vch%2F8%2BGrUc%2FBH3nJvoOjMHUuvycgsJ5gkS1mCH428lrIjqHNbN%2FCrL2Pp%2F%2BScOgNNYWeVlZi8dilTpMWS7AqDzL110u9tfozo2ARYO%2F35y5C%2BJMdf5GsAPXFS9uvx4jslq4mxXrUetywL80haMZBObyC49bKxrheyQ%3D%3D%7Ctkp%3ABk9SR9rStPbvZw",
          "img": "https://i.ebayimg.com/images/g/FMQAAeSwpZxpuNDO/s-l500.jpg",
          "sd": "Jun 6, 2026"
        },
        {
          "t": "Marshadow & Machamp GX (Full Art) 199/214 Sm-Unbroken Bonds Holo BGS 9!! PSA 10!",
          "p": 442,
          "u": "https://www.ebay.com/itm/278012264811?_skw=marshadow+machamp+GX+199+full+art+PSA+9+-lot+-secret+-rainbow&epid=9065727749&itmmeta=01KXZPD557X1AEE6VFKEHZ8C8D&hash=item40bad2816b:g:eTAAAeSw5ptqEHzr&itmprp=enc%3AAQALAAABIGfYFPkwiKCW4ZNSs2u11xBCuerWU9aOll%2BEmdKFoHfC176Z6TY9NuY5MP9DIOmMv10ycBoPgFRW74ukYlyvsn7DLE651ozrNaPLbiaBo6l6r9fFKjNAlDdz14LdOQpJ0EKADRebA1hnXEdy1zffMYKkhte3ViS4v%2BBMgwfRuGCkx89v0gDPerfgDNePOUMnsPaB2njAT5WtPGuQA%2F2%2Bu36%2BGN1apS8eh52b7GCJwGgulvIHQlch4TVdW80omY9WAxvSjo%2B5InEFo%2BSWuQjjabf3Bz0HB8SH%2B%2FwEPCiptg1DDA%2BcUwz4YWr9yxMZAP0FQy4nmQvOBs5ehKaJpcc%2B35sR3j4dwwOPvj7T0bhjKq7%2B4jmxtivT9aKTs5s0KGlskg%3D%3D%7Ctkp%3ABk9SR9rStPbvZw",
          "img": "https://i.ebayimg.com/images/g/eTAAAeSw5ptqEHzr/s-l500.jpg",
          "sd": "Jun 2, 2026"
        },
        {
          "t": "Marshadow & Machamp GX Full Art Ultra Rare Holo 199/214 Unbroken Bonds PSA 9",
          "p": 408,
          "u": "https://www.ebay.com/itm/277843221196?_skw=marshadow+machamp+GX+199+full+art+PSA+9+-lot+-secret+-rainbow&epid=9065727749&itmmeta=01KXZPD557NS8VHNK2W3016QAB&hash=item40b0bf1acc:g:NZgAAeSw47FpyAMp&itmprp=enc%3AAQALAAABIGfYFPkwiKCW4ZNSs2u11xBYyJS7EHG6NaVtlY--mlU8450zmQANzAl7f6sIWmNlvve39GmQeok2tu2h9ntBQiIW%2FNfLFmgDc0DP9x9uHVHgpfdvdZ3PsfwID2F4hgvpCcIYakfP1oeowlF2D8MhGN0gmUkQ37HDQdYM5nrOnzCNdH1n5ZwjAP2NN0Z7n29bTsvIJFIZzj1ECI12bo5hOwtImkhH7iB3OOzUJU6tvzJ3TYXfhabneJ41sTCtOY5HFOViq0NHFWdKkie55NFnBmhdDfqLlP0NclYXf1Bk56xORv0TA0B0yxsKHIrArZiD8emEK4Emt4BLDRXEYPZs4SftDbrpsfJpBQsOUzBQq8i8zDBkapLoC31jmI654osZcw%3D%3D%7Ctkp%3ABk9SR9rStPbvZw",
          "img": "https://i.ebayimg.com/images/g/NZgAAeSw47FpyAMp/s-l500.jpg",
          "sd": "May 17, 2026"
        }
      ],
      "img": "https://i.ebayimg.com/images/g/FMQAAeSwpZxpuNDO/s-l500.jpg"
    },
    {
      "ticker": "$GARDV",
      "name": "Mega Gardevoir ex MEP 032 · Poster Coll · PSA 10",
      "cost": 160,
      "prev": 359.71,
      "now": 352.24,
      "color": "#b07cff",
      "floor": 250,
      "queries": [
        "mega gardevoir ex 032 PSA 10 -lot -charizard -lucario",
        "gardevoir ex MEP 032 PSA 10 -lot -lucario"
      ],
      "listings": [
        {
          "t": "2026 POKEMON MEP EN-ME BLACK STAR PROMO #032 MEGA GARDEVOIR EX PSA 10",
          "p": 388,
          "u": "https://www.ebay.com/itm/306911936923?_skw=gardevoir+ex+MEP+032+PSA+10+-lot+-lucario&epid=17091916586&itmmeta=01KXQZ6N9BR2ZCFX3C5K5GFZEM&hash=item477560819b:g:cZoAAeSwAnFp9H74&itmprp=enc%3AAQALAAABEGfYFPkwiKCW4ZNSs2u11xB2YtpWioBrYPIPgUNpAuKwVLYrSY3CFdZJHZ88iEC6W%2Fqkelwr0nwNwadTKAI1NUw88jOshrBm5fIJQc6mmX44%2FUL4vdlEqCREZbcHOF3L1TG7JBU2zXew%2F7ZtANZuPJRcDQnmENod%2FRQrI%2Byh%2BAniqlF0S27XsJQz%2Bu%2FGQv8n0W%2FxEa8slmqK8KUnquyF2yqoxniSk21GV0a%2B2mooafSZFiakSEGEBuDUv%2BupFyt4i4l6i9GF0iP78%2F0LgZsSFgghrn9ago2WxOwdWnaW%2BufRsaqflKG%2Fx467uYfg1W1vIueIsWfpDsIxYUMWiVROSbmp3BTHhayeuYu0OBgYOJ8B%7Ctkp%3ABk9SR-LUmv_tZw",
          "img": "https://i.ebayimg.com/images/g/cZoAAeSwAnFp9H74/s-l500.jpg",
          "sd": "May 4, 2026"
        }
      ],
      "img": "https://i.ebayimg.com/images/g/cZoAAeSwAnFp9H74/s-l500.jpg"
    },
    {
      "ticker": "$HAWL",
      "name": "Mega Hawlucha ex 268/217 · Ascended Heroes · PSA 10",
      "cost": 160,
      "prev": 231.2,
      "now": 231.2,
      "color": "#ff8a5d",
      "floor": 150,
      "queries": [
        "mega hawlucha ex 268/217 PSA 10 -lot",
        "hawlucha ex 268 PSA 10 -lot"
      ],
      "listings": [
        {
          "t": "Mega Hawlucha ex 268/217 Me: Ascended Heroes Holo - Mega Attack Rare - PSA 10",
          "p": 231,
          "u": "https://www.ebay.com/itm/198422527908?_skw=hawlucha+ex+268+PSA+10+-lot&epid=26090323694&itmmeta=01KXZPFYTZQYQ0F5C9DSD8B4D0&hash=item2e32e77fa4:g:GeEAAeSw9TlqLMhl&itmprp=enc%3AAQALAAABAGfYFPkwiKCW4ZNSs2u11xBqU3PWUOA16ws3N52kIeBJytZIPOMj5SCaALY9du53enlzjh5ylIrrFvr28Uc%2BeUddZykVhNyJ5Y3HR7Mw75i%2BI5k%2BMST5Gn3UjAJ%2BBmsPRNyzCKj3QxudRunn7UgcQZ9hZUARxQjVLDcY7wbUrUwolcZ5aryI%2BCgVwaI6iGDYwQodV%2B1Z2kZlhrYtGmwkF8fHj7aapjNz9Poy6eDiemuQKIjkiw3L5aqYCRAEJzRaLpOH6TEMKJc8p3NZlDuSImWS0aFtAf5C3TvJ%2Bm4M7skULnwJNXMfTlrSxjjWm4jWf3K0hAQuj8hwwPpKXWAuZF0%3D%7Ctkp%3ABk9SR87tv_bvZw",
          "img": "https://i.ebayimg.com/images/g/GeEAAeSw9TlqLMhl/s-l500.webp",
          "sd": "Jun 16, 2026"
        },
        {
          "t": "2026 Pokemon Asc En-Ascended Heroes 268 Mega Hawlucha Ex Mega Attack Rare PSA 10",
          "p": 265,
          "u": "https://www.ebay.com/itm/358591562232?_skw=hawlucha+ex+268+PSA+10+-lot&epid=26090323694&itmmeta=01KXZPFYTZPWQTVX4S9BYFMSWW&hash=item537db901f8:g:zrYAAeSwYudqEliO&itmprp=enc%3AAQALAAAA4GfYFPkwiKCW4ZNSs2u11xDf1gIRM%2FyR5IczXJOPcCv%2BcqnrkYMvpOkGMOKXZ58H3i7p131Hsjrxv%2Fi6Q%2Fzx4Z6%2B21lvtYZjpudZ716kmMa%2Fx5znciyGzQUS%2BdshzMDNh%2FA3rpibzDp9zxCOnbMbLGKd%2BuIu5ZkzSNgDnxdG2UhTnqIz2YC%2FG9EcrrTw9CjtamtGOfa3u1WPuHJqq7%2BZaFHVJ2bEHFSaZd0EOpSYJ73C4lxMsxUb0InruVkdwOhMMeRvpPj%2BDOOjXb55BswZvFwDJ7FGvfyr%2Fn6S0fZ8xWMg%7Ctkp%3ABk9SR87tv_bvZw",
          "img": "https://i.ebayimg.com/images/g/zrYAAeSwYudqEliO/s-l500.webp",
          "sd": "May 26, 2026"
        },
        {
          "t": "Pokemon TCG Mega Hawlucha ex 268/217 Ascended Heroes Holofoil PSA 10 MINT ATTACK",
          "p": 231,
          "u": "https://www.ebay.com/itm/188383316986?_skw=hawlucha+ex+268+PSA+10+-lot&epid=26090323694&itmmeta=01KXZPFYTZ79WRQS6CF56RA10F&hash=item2bdc854bfa:g:zQYAAeSweUpqAT6b&itmprp=enc%3AAQALAAAA4GfYFPkwiKCW4ZNSs2u11xAneb5TkZC2KpFIKqXnaSdVI%2FOWHyQCbvvOi3OK74lPP%2BWClSW8Yi76m8M3fI0psvy2Ja8IPdcCFbKNZKVvGmKzEpfuRN%2BR8%2FhXW1Rzrl546iJDtpF6Wee1z1e9AYdLf%2BVnsOzyOqb%2BCMmDMpER3WfRx2Z15uCYpFh8R38t43bJkByBqkPIrWCXJjthijntiM%2BkH%2BU0YYz9TienM7JmnxJyahpW%2FXk1fX5Dtx1BoHlC%2BtTsCP2nG2f22zYx2jekRsfwfV470wEZEQLU0DAro00k%7Ctkp%3ABk9SR87tv_bvZw",
          "img": "https://i.ebayimg.com/images/g/zQYAAeSweUpqAT6b/s-l500.webp",
          "sd": "May 14, 2026"
        }
      ],
      "img": "https://i.ebayimg.com/images/g/GeEAAeSw9TlqLMhl/s-l500.webp"
    },
    {
      "ticker": "$EEVEE",
      "name": "Eevee 074/131 · Pokémon Day 2025 Stamp · PSA 10",
      "cost": 150,
      "prev": 235.27,
      "now": 235.27,
      "color": "#ffcb52",
      "floor": 150,
      "queries": [
        "2025 eevee pokemon day psa 10 -lot",
        "eevee 074/131 pokemon day psa 10 -lot"
      ],
      "listings": [
        {
          "t": "Eevee Prismatic Evolutions 074/131 Holo Pokemon Day 2025 Stamped Promo PSA 10",
          "p": 235,
          "u": "https://www.ebay.com/itm/286859951161?_skw=2025+eevee+pokemon+day+psa+10+-lot&itmmeta=01KXZPGDH302N2G3M8FKTC06ZZ&hash=item42ca2f7c39:g:7o0AAeSwCupo4sAS&itmprp=enc%3AAQALAAABAGfYFPkwiKCW4ZNSs2u11xBA2SWR3Xlw8SoMw%2BbpXbM7iJtSCPEU9hpLUtDaWWA50J4y1A29pFZgbVskWMaHKiAGREFqsxdg4r%2FZ2cNfVEoUjkubcnl3MDt8ltckIjWLyjLYlL6peFuAwreL0WNKYPUkWcmbJkrEYIMwpynPfSAhbUnHutXC2M6wbkakzkLqMxVdVhVVZoA6zZ1pL%2BmKSJCSXed7%2By%2BNIValJS2QsBYqmmmm6SgDSgCOprm2chmS7mXBU96gKV79jN633%2B75V%2Fb%2FrvKI48nWN%2BaC0%2F26s6n%2FQR%2FDQOiIZOKOodA28A6QhUnMkYWKobUdQk2ICi3Of%2B4%3D%7Ctkp%3ABk9SR_DYwfbvZw",
          "img": "https://i.ebayimg.com/images/g/7o0AAeSwCupo4sAS/s-l500.webp",
          "sd": "Jul 4, 2026"
        },
        {
          "t": "Eevee Pokemon Day 2025 Promo Cosmic Holo PSA 10",
          "p": 218,
          "u": "https://www.ebay.com/itm/406975355507?_skw=2025+eevee+pokemon+day+psa+10+-lot&epid=15075317378&itmmeta=01KXZPGDH4JHYMXTDQN8Z8R3G1&hash=item5ec19f1a73:g:YtYAAeSwspZqIPZe&itmprp=enc%3AAQALAAABAGfYFPkwiKCW4ZNSs2u11xAeJ2qtp7vVP6bI3QVkiLqmlqMamnyQm6aM%2BM3gvDvr2qCjhcPInSatgrfuucO4h%2BIP3I4TnxuBpRa4I6NRDdS1j4cAsasMVccTQlEZY%2BNXrBl082nhXU0GqMIGXnP%2BgkHZ2OyA8A4bB79BvGtZGxr3X%2Bk%2BNl1Ofnlqaf69AMWsITPdo6YBgtet6SlASpVzfwyfrxNLmYyKBm7h3KpC75lOy8EDReCmYPRThQWufkwNGnsHoD6ZJVX%2BtIzhmDf6Mpye9rzqlt1p7NYTra498lczaiBbzIdqJtqA8vuhkk53iTgwyMU9%2F8lMVqbWcX4pir8%3D%7Ctkp%3ABk9SR_TYwfbvZw",
          "img": "https://i.ebayimg.com/images/g/YtYAAeSwspZqIPZe/s-l500.webp",
          "sd": "Jun 17, 2026"
        },
        {
          "t": "Pokemon TCG Prismatic Evolutions - Pokemon Day 2025 Eevee #074 - PSA 10",
          "p": 237,
          "u": "https://www.ebay.com/itm/188430452105?_skw=2025+eevee+pokemon+day+psa+10+-lot&itmmeta=01KXZPGDH56DNGVEH205VQ8W2H&hash=item2bdf548589:g:8wEAAeSwVKVqFsVz&itmprp=enc%3AAQALAAABAGfYFPkwiKCW4ZNSs2u11xAjp0hIjgWAgX%2FqfRNKJCMOD%2F7F2a%2BrIgAEEaZsWGDlvvCWTelZihNzO28gUOURAYZXuMjfImENz%2FaEOU4JjkDer9TmPQ7wzUEJKxXkQLCNuagt0DxW4QjE9RTwJPU8cNVlhpnNaD8jkhR3dRnm10MT5O6Pj4iUQ2xYQ1U7Q8TtbszUPNInKU0EbqAu%2BE0r4dtf7ld3GUsAk0jnh0nQnnie7El5NxvwHus6DkWdsG14GMBfPp%2FzJHuoY33RTmcLD8cpaaHDw4Urkm052WyuM%2FL28anObh0YDhyetqRDh4T0mlTj7NGGCDbprEzAVMTVbJo%3D%7Ctkp%3ABk9SR_TYwfbvZw",
          "img": "https://i.ebayimg.com/images/g/8wEAAeSwVKVqFsVz/s-l500.webp",
          "sd": "Jun 6, 2026"
        }
      ],
      "img": "https://i.ebayimg.com/images/g/7o0AAeSwCupo4sAS/s-l500.webp"
    },
    {
      "ticker": "$FLAR",
      "name": "Flareon · 1999 Jungle #3 Holo · PSA 7",
      "cost": 109,
      "prev": 108.8,
      "now": 108.8,
      "color": "#fb923c",
      "floor": 40,
      "queries": [
        "flareon jungle holo PSA 7 -1st -lot",
        "flareon 3/64 PSA 7 -1st -lot",
        "flareon jungle PSA 7 unlimited -lot"
      ],
      "listings": [
        {
          "t": "Flareon Holo 136 Jungle Pokemon Japanese PSA 7",
          "p": 102,
          "u": "https://www.ebay.com/itm/398061456235?_skw=flareon+jungle+holo+PSA+7+-1st+-lot&epid=14066000823&itmmeta=01KXZPJ81H5E85ABVVKC2J7TH5&hash=item5cae4fcb6b:g:2f0AAeSwHk1qMbDG&itmprp=enc%3AAQALAAABAGfYFPkwiKCW4ZNSs2u11xC2t3sulMZkehoSjQ5wXGMUl3M2xe7dQZY7s8YdQG9AD9pAjRsMSGzAmfK3gN2Oej0l4ukj5uRDGcosi5OT09XL%2BLYH1bcKq%2FRV9JNQ67XP7tzH5aLMla7rkYQ%2FmZdqfbtDYgJI1Ax2mjfbRoVvx1DdCxXlELAu5EyIGYzlzgY%2FG14hjrtfa4S3TOUy1AFtn0V7sDrRkblrlGnLyIVyxEh02v%2BbGPWNevVG0opYXow7IOy4CP75ZET41uRB6nY7Z8jaWiRApBhpyZhtHPUWMhTZtNv5%2BQocXpbLt94M5JjdKs3taSPwE%2Brh3IwyrVAlcUA%3D%7Ctkp%3ABk9SR_SAyfbvZw",
          "img": "https://i.ebayimg.com/images/g/2f0AAeSwHk1qMbDG/s-l500.webp",
          "sd": "Jul 19, 2026"
        },
        {
          "t": "Flareon Holo #3 Jungle 1999 Pokemon PSA 7",
          "p": 113,
          "u": "https://www.ebay.com/itm/287432121136?_skw=flareon+jungle+holo+PSA+7+-1st+-lot&epid=13043374721&itmmeta=01KXZPJ81HMA62FE2803ZFCVM8&hash=item42ec4a1b30:g:77wAAeSwsvBqN~ql&itmprp=enc%3AAQALAAAA4GfYFPkwiKCW4ZNSs2u11xAsprblSq6Iu%2FDpoq9Sch3ICJcwHkZjzGqdXRa9EOAayEBallQdFQXvnrPbqY3K8eGcnAsxA%2BhBrZjF1EtA24vBfC3R14ahHZCCi2tB7cBFWCLDktaJUSLZndbB%2BSlwDPbO%2F%2B%2B%2FPvyWQ8sa3mOG826OrkkU7AMFb5U3pqWNkBmI7PWfRGvVIbZF%2FtBV2yAaR2uK1Tct4Z2keCptJLqTOveeHsL%2BtnxNyZPU%2FQHD1gCOMrauifZw%2BcjAoGaHvqkMB9wvpw5p0JaAZdPYodgPrYzG%7Ctkp%3ABk9SR_SAyfbvZw",
          "img": "https://i.ebayimg.com/images/g/77wAAeSwsvBqN~ql/s-l500.webp",
          "sd": "Jul 8, 2026"
        },
        {
          "t": "1999 Pokémon TCG Flareon Holo Rare Card Base Set Jungle PSA 7 NM",
          "p": 122,
          "u": "https://www.ebay.com/itm/298243846434?_skw=flareon+jungle+holo+PSA+7+-1st+-lot&epid=13043374721&itmmeta=01KXZPJ81JZME62S2K1F4QJETA&hash=item4570b7f122:g:9DIAAeSw8kxp5XL7&itmprp=enc%3AAQALAAAA4GfYFPkwiKCW4ZNSs2u11xC%2FjLvjtq0Shail8G125eX2ajjKaPhKTGs2KC52vziJK8dg60wLYoVexjE1F4cuYWyznjdfVD2LYJyxerCqMfQ4AgrsjTLcTP90OBxYng3pRJxOh761WgH0y0tozxMBtOBQrC94dEDMEuIRSr3OPGJ3ShnwKqRwVbVVhVzSYesz%2BGDyPC01bXoownF%2FK74ymQQ6l0fj3hF3flYp97J54WlDp%2BRh5%2BVCBKNeAXQS%2BA97BSUqJyERIuyx2Qo3DwuChuHotcmZXPJzqZf7AjvpYklN%7Ctkp%3ABk9SR_SAyfbvZw",
          "img": "https://i.ebayimg.com/images/g/9DIAAeSw8kxp5XL7/s-l500.webp",
          "sd": "Jul 7, 2026"
        }
      ],
      "img": "https://i.ebayimg.com/images/g/2f0AAeSwHk1qMbDG/s-l500.webp"
    },
    {
      "ticker": "$LUCARIO",
      "name": "Mega Lucario ex MEP 033 · Poster Coll · PSA 10",
      "cost": 210,
      "prev": 509.82,
      "now": 510.0,
      "color": "#3b7dd8",
      "floor": 350,
      "ceil": 900,
      "queries": [
        "mega lucario ex 033 PSA 10 -lot -gardevoir",
        "mega lucario ex MEP 033 PSA 10 -lot"
      ],
      "listings": [
        {
          "t": "2026 POKEMON MEP PROMO PREMIUM POSTER COLLECTION #033 MEGA LUCARIO EX PSA 10",
          "p": 483,
          "u": "https://www.ebay.com/itm/298400911648?_skw=mega+lucario+ex+MEP+033+PSA+10+-lot&epid=17091916394&itmmeta=01KXG820ATTBB20W9W4NZSTH9B&hash=item457a149120:g:pHAAAeSwE-hqKK~T&itmprp=enc%3AAQALAAABAGfYFPkwiKCW4ZNSs2u11xAnhWy0B1txdgdrfuz%2BuNhmpVePchkiFDnGcoawH7KJJu3NLK%2BLKHWJ1Y5zxJNCAV%2BDsVNiqXIHcOi781Ww0YanTw0cwjAjczHpccXgVsJW7YDX4HEFC3l0jZ1nbjsJE0%2BgSfsm0sB7i%2BEMwUpArDtQCUNo9o6YAnnlb0PtEKnu8nfe7GDFcmHv1A6pXaVEe9S98UiXr32tr%2BCyLu4mRzK8LbVonuSTpvZeXfeaAp3tZqwf2OcPqy5nbEOZbK0Ku4bwJCYIYudd7uyIqq%2BPdkimP6quxXXiSQcRXueF8pcas9OKeOMPAuXalLflgAovsgs%3D%7Ctkp%3ABk9SR86FiIjsZw",
          "img": "https://i.ebayimg.com/images/g/pHAAAeSwE-hqKK~T/s-l500.webp",
          "sd": "Jun 21, 2026"
        }
      ],
      "img": "https://i.ebayimg.com/images/g/pHAAAeSwE-hqKK~T/s-l500.webp"
    },
    {
      "ticker": "$LUFFY16",
      "name": "Luffy OP16-034 · Time of Battle · Alt Art raw",
      "cost": 0,
      "prev": 57.61,
      "now": 57.58,
      "color": "#2eaa5e",
      "floor": 40,
      "ceil": 200,
      "queries": [
        "luffy OP16-034 alt art -PSA -CGC -lot",
        "monkey d luffy OP16-034 -PSA -CGC -lot"
      ],
      "listings": [
        {
          "t": "Monkey.D.Luffy (034) (Alternate Art) OP16-034 The Time of Battle Foil",
          "p": 249,
          "u": "https://www.ebay.com/itm/377315477716?_skw=monkey+d+luffy+OP16-034+-PSA+-CGC+-lot&epid=18094779118&itmmeta=01KXDNNDX4EGKQ6R4FSHZ13KJC&hash=item57d9c148d4:g:5I8AAeSwkPFqR-bX&itmprp=enc%3AAQALAAABAGfYFPkwiKCW4ZNSs2u11xCEPb2bUhs97sxgEGBs0L3mrYZZQs7vkz7D7TvPFX7dEMb%2F5x2GcasU9vfGCZHiyvj%2BK20X9UWbzmcpk%2BljiAtk6euvWz1otn51dPjguoQ4BQzXsK%2FoXNkJx3muEjqV5qQAdC2bUMo0ApomJLvWv3ZUlwSc3s5kZunBfUE3FC10IV1a6iO5oafbCeGkT22%2BGhtBplVzXCdb7AYb7%2FB0YOBgWIjlv4UTu6OV2tpXWwyY5blJAa8tWzZy2TZ1r5p1wxfAUaNsFnN6SyLHkfPqhGLLXI4ePvwVqwi%2FV0gjCJrWu6hI%2BDF4AGiuVzbENYi0K%2B0%3D%7Ctkp%3ABk9SR97e1bXrZw",
          "img": "https://i.ebayimg.com/images/g/5I8AAeSwkPFqR-bX/s-l500.webp",
          "sd": "Jul 10, 2026"
        },
        {
          "t": "4x OP16-034 Monkey D Luffy R Playset -One Piece TCG- The Time of Battle English",
          "p": 99,
          "u": "https://www.ebay.com/itm/188611896321?_skw=monkey+d+luffy+OP16-034+-PSA+-CGC+-lot&itmmeta=01KXDNNDX5B76SPKWEECWK03PA&hash=item2bea252401:g:EkIAAeSw505qTPux&itmprp=enc%3AAQALAAAA4GfYFPkwiKCW4ZNSs2u11xDXZgVOukp1DK9Y8fXoq37yigBVR7xanCTXA2sTqFB7r9UUdkB5ns9X8GzyIJExZ2YUaEUz3gMeAYncwIM4%2FOUwbh61vh%2FY%2BQP7NiPsBJMF05pWFA8UQyVtdzoU5PI2%2F1o8PJ%2Fs%2Fr9TmzDIxTTzl8RAMeCQ%2F5iMPhyeQfpet%2FPle6FzE%2BA6K09NO1YIjrOsuxPCHjfHTfqZt08rvOVKNuwtj80IQ152qPTRvmWFpEE1re1G0GO9fOpTebu7Q798UwIrjqJ7Dbv4tbZnLTNCBYBK%7Ctkp%3ABk9SR97e1bXrZw",
          "img": "https://i.ebayimg.com/images/g/EkIAAeSw505qTPux/s-l500.webp",
          "sd": "Jul 10, 2026"
        },
        {
          "t": "Monkey.D.Luffy (034) OP16-034 Foil The Time of Battle Grade 10",
          "p": 62,
          "u": "https://www.ebay.com/itm/366506501621?_skw=monkey+d+luffy+OP16-034+-PSA+-CGC+-lot&epid=18094779119&itmmeta=01KXDNNDX55C4ERDG4AYK2P7EJ&hash=item55557d65f5:g:n6kAAeSw9tRqP03J&itmprp=enc%3AAQALAAAA4GfYFPkwiKCW4ZNSs2u11xCvgW6PYaMM4TctWtKTM8ryyrDJaUDnE%2Bt9nl2aHkb7XGOD2u8BGdlIJ%2FwvEGZVtsSKGUqYEXxHFqQIFFzFApXkvwzbg1AQra1owoHCZnxzZnUFjhxt7HSedtSMWbRTrAK22IwnOTyj%2FrAWAkDkpDE3GAsLygVnF27dnEW29PxQX8wmKfOCMEIW2UZ6mZxB8cp0kqbOBY62H0X2M--XciO0W6hRvOLzqOe8Xo%2BQjF4YdQ07a0LjTwJYz%2BMPoLQtKBngOqpp2MzZWvRK%2FWCnL%2Bjy%7Ctkp%3ABk9SR97e1bXrZw",
          "img": "https://i.ebayimg.com/images/g/n6kAAeSw9tRqP03J/s-l500.webp",
          "sd": "Jul 8, 2026"
        }
      ],
      "img": "https://i.ebayimg.com/images/g/5I8AAeSwkPFqR-bX/s-l500.webp",
      "pending": 99.47
    },
    {
      "ticker": "$MAGNETON",
      "name": "Dark Magneton 11/82 · Team Rocket 1st Ed · PSA 7",
      "cost": 100,
      "prev": 121.72,
      "now": 122.4,
      "color": "#9aa0a6",
      "floor": 30,
      "ceil": 250,
      "queries": [
        "dark magneton team rocket 1st edition PSA 7 -lot",
        "dark magneton 11/82 1st edition holo PSA 7 -lot"
      ],
      "listings": [
        {
          "t": "2000 Pokemon Rocket Dark Magneton Holo 11/82 1st Edition PSA 7",
          "p": 129,
          "u": "https://www.ebay.com/itm/137521783521?_skw=dark+magneton+11%2F82+1st+edition+holo+PSA+7+-lot&epid=22043374877&itmmeta=01KXZPPX4S95QGP5Q5F69AB10V&hash=item2004efe2e1:g:n1EAAeSwlDZqWhBP&itmprp=enc%3AAQALAAABEGfYFPkwiKCW4ZNSs2u11xBHUgzsFgVAbnttFD%2BT3lCjnXQSR6rGZjgJP0SCJfc3uqn9s%2BpljJlbABMLzO%2BJAzdtfCfQdUGIp6NRhPiC3i69%2FUo5mxBC%2FU%2B2QYF4o3Ird9umnUCTQ7%2FhQhYJlpMrLoop1NrTrt2twsPXVHxjSGtJsUR3Zn7zI3LvZnaTu4%2Fy%2FwwzOACKot1PxJlb1CsvhC5WlmoTWNoK3ORqxDW3QQtFeEuQ%2BHTeo6JmhNO%2FvxshKOb7F0uKFLYWAxBe%2FowJzsj4CE85Dl8whnnrJWofQLfNa%2BtM8MRUxovsfX5N3mpObTdieLfayOZJY3FDidP546xvyrTVsOz5u8HoaPj7jSLG%7Ctkp%3ABk9SR8DS2_bvZw",
          "img": "https://i.ebayimg.com/images/g/n1EAAeSwlDZqWhBP/s-l500.webp",
          "sd": "Jul 17, 2026"
        },
        {
          "t": "PSA 7 2000 Pokemon Team Rocket Dark Magneton 11/82 1st Edition Holo EN",
          "p": 143,
          "u": "https://www.ebay.com/itm/227431352994?_skw=dark+magneton+11%2F82+1st+edition+holo+PSA+7+-lot&epid=22043374877&itmmeta=01KXZPPX4SSPFH83AKDG2PJR7V&hash=item34f3f70aa2:g:rGIAAeSwRTtqVpkh&itmprp=enc%3AAQALAAAA8GfYFPkwiKCW4ZNSs2u11xDiS47oPr25l4YPo%2F8%2BuhfYmxBgXv1C7UWQX1wTc%2Fh9wgd1KmgekFpDtseQHBPNdL1o7EyVxzQ9OZOXUY8fVSy6lUnGxXrjVYF1lDe%2FOC0hyM6ijMsEMZO5mTt2udLvhDp8CEo%2BGwUpdlg%2BkSpnJZEjAwc3DILd4HONuZ%2Fn8XsrzgesCSOH2fEtIniUjsTC%2FtmH5vNS53tLkcZXT5ay9vG1pm4KQj1IemglDEVew6QhsMvGKwkok51AV9wOSTw7K9VKGPKVNteYylrNTex2H5wQUwj5vWOLwbVD7Fn1x13EXw%3D%3D%7Ctkp%3ABk9SR8DS2_bvZw",
          "img": "https://i.ebayimg.com/images/g/rGIAAeSwRTtqVpkh/s-l500.webp",
          "sd": "Jul 16, 2026"
        },
        {
          "t": "2000 Pokemon Rocket Dark Magneton Holo 11/82 1st Edition PSA 7",
          "p": 121,
          "u": "https://www.ebay.com/itm/366537306795?_skw=dark+magneton+11%2F82+1st+edition+holo+PSA+7+-lot&epid=22043374877&itmmeta=01KXZPPX4S4WEF5C8WFX5FG4MK&hash=item55575372ab:g:apQAAeSwAzZqUtIE&itmprp=enc%3AAQALAAAA8GfYFPkwiKCW4ZNSs2u11xCM%2BBjs99%2FB4SKUN%2FmWFua2%2Fhq3KrQ95lMvE62hJqniOT2H0aME%2Fzcx%2BtVDutsK7bGcpGvvpSC%2BIh3H%2BA58%2BLL1oL7DCjcMxJj2gk%2FwjlaFf9yDIhBPtHjE8ycQEGryA20ynS%2FHR8AZYwjBATgttenBXbukWr2DEpnN6ZVQ8%2BkVYe3jaDORYFe34FprWMKmDVfjLnZMuZgZA0Q%2BSPCfSvgrUxBn6iy0JZY%2FUeL4d3FZEu62vxVNF3W%2Ftq9KKpuufnzanfXhwPPwsaxBy8EbmSsctiOiVctklMq6woaxyhOnRw%3D%3D%7Ctkp%3ABk9SR8DS2_bvZw",
          "img": "https://i.ebayimg.com/images/g/apQAAeSwAzZqUtIE/s-l500.webp",
          "sd": "Jul 13, 2026"
        }
      ],
      "img": "https://i.ebayimg.com/images/g/n1EAAeSwlDZqWhBP/s-l500.webp"
    }
  ]
}